fprime_visual/__init__.py
fprime_visual/__main__.py
fprime_visual/flask/__init__.py
fprime_visual/flask/app.py
fprime_visual/flask/static/css/style.css
fprime_visual/flask/static/img/f-logo-gradient.png
fprime_visual/flask/static/img/info.png
fprime_visual/flask/static/img/screenshot.png
fprime_visual/flask/static/js/helpers.js
fprime_visual/flask/static/js/script.js
fprime_visual/flask/static/js/typedefs.js
fprime_visual/flask/static/js/layouts/basic-layout.js
fprime_visual/flask/static/js/layouts/layouts.js
fprime_visual/flask/static/js/lib/elkjs/LICENSE.md
fprime_visual/flask/static/js/lib/elkjs/elk-api.d.ts
fprime_visual/flask/static/js/lib/elkjs/elk-api.js
fprime_visual/flask/static/js/lib/elkjs/elk-worker.d.ts
fprime_visual/flask/static/js/lib/elkjs/elk-worker.js
fprime_visual/flask/static/js/lib/elkjs/elk-worker.min.js
fprime_visual/flask/static/js/lib/elkjs/elk.bundled.d.ts
fprime_visual/flask/static/js/lib/elkjs/elk.bundled.js
fprime_visual/flask/static/js/lib/elkjs/main.d.ts
fprime_visual/flask/static/js/lib/elkjs/main.js
fprime_visual/flask/static/js/renderers/index.js
fprime_visual/flask/static/js/renderers/render-basic.js
fprime_visual/flask/static/js/renderers/render-elk.js
fprime_visual/flask/static/js/renderers/helpers/box.js
fprime_visual/flask/static/js/renderers/helpers/render-utils.js
fprime_visual/flask/static/js/themes/dark-blue.js
fprime_visual/flask/static/js/themes/dark.js
fprime_visual/flask/static/js/themes/default.js
fprime_visual/flask/static/js/themes/light-seafoam.js
fprime_visual/flask/static/js/themes/new-light.js
fprime_visual/flask/templates/index.html
fprime_visual-1.0.2.dist-info/LICENSE.txt
fprime_visual-1.0.2.dist-info/METADATA
fprime_visual-1.0.2.dist-info/WHEEL
fprime_visual-1.0.2.dist-info/entry_points.txt
fprime_visual-1.0.2.dist-info/top_level.txt
fprime_visual-1.0.2.dist-info/RECORD
