Metadata-Version: 2.1
Name: fprime-visual
Version: 1.0.2
Summary: F Prime Prime (FPP) model visualization tool
Author-email: Thomas Boyer-Chammard <Thomas.Boyer.Chammard@jpl.nasa.gov>, Michael Starch <Michael.D.Starch@jpl.nasa.gov>
License:                                  Apache License
Project-URL: Homepage, https://fprime.jpl.nasa.gov
Project-URL: Documentation, https://nasa.github.io/fprime/
Project-URL: Repository, https://github.com/fprime-community/fprime-visual
Keywords: fprime,embedded,nasa,flight,software
Classifier: Development Status :: 5 - Production/Stable
Classifier: Intended Audience :: Developers
Classifier: Operating System :: Unix
Classifier: Operating System :: POSIX
Classifier: Programming Language :: Python
Classifier: Programming Language :: Python :: 3
Classifier: Programming Language :: Python :: 3.8
Classifier: Programming Language :: Python :: 3.9
Classifier: Programming Language :: Python :: 3.10
Classifier: Programming Language :: Python :: 3.11
Classifier: Programming Language :: Python :: 3.12
Classifier: Programming Language :: Python :: Implementation :: CPython
Classifier: Programming Language :: Python :: Implementation :: PyPy
Classifier: License :: OSI Approved :: Apache Software License
Requires-Python: >=3.8
License-File: LICENSE.txt
Requires-Dist: flask>=3.0.0
Requires-Dist: flask_compress>=1.11
Requires-Dist: pytest>=6.2.4
Requires-Dist: flask_restful>=0.3.8
